beanstatement/__init__.py
beanstatement/reporter.py
beanstatement/reporter_test.py
beanstatement/scripts/__init__.py
beanstatement/scripts/main.py
beanstatement/templates/__init__.py
beanstatement/templates/balance_sheet.mustache
beanstatement/templates/income_statement.mustache
beanstatement/test_resources/__init__.py
beanstatement/test_resources/minimal/__init__.py
beancount_financial_statement-0.8.5.dist-info/METADATA
beancount_financial_statement-0.8.5.dist-info/WHEEL
beancount_financial_statement-0.8.5.dist-info/entry_points.txt
beancount_financial_statement-0.8.5.dist-info/top_level.txt
beancount_financial_statement-0.8.5.dist-info/RECORD
