Metadata-Version: 2.1
Name: beancount-financial-statement
Version: 0.8.5
Summary: A report generator for beancount financial statement.
Home-page: https://github.com/e7h4n/beancount-financial-statement
Author: e7h4n
Author-email: ethan.pw@icloud.com
Project-URL: Bug Reports, https://github.com/e7h4n/beancount-financial-statement/issues
Project-URL: Source, https://github.com/e7h4n/beancount-financial-statement/
Keywords: beancount,financial statement
Classifier: Development Status :: 4 - Beta
Classifier: Intended Audience :: Financial and Insurance Industry
Classifier: Topic :: Office/Business :: Financial :: Accounting
Classifier: License :: OSI Approved :: MIT License
Classifier: Programming Language :: Python :: 3
Classifier: Programming Language :: Python :: 3.6
Classifier: Programming Language :: Python :: 3.7
Classifier: Programming Language :: Python :: 3.8
Classifier: Programming Language :: Python :: 3.9
Classifier: Programming Language :: Python :: 3 :: Only
Requires-Python: >=3.6, <4
Requires-Dist: logzero >=1.7.0
Requires-Dist: click <9,>=7
Requires-Dist: pystache >=0.6.0
Requires-Dist: beancount >=2.3.6
Provides-Extra: dev
Provides-Extra: test
Requires-Dist: coverage ; extra == 'test'
Requires-Dist: pycodestyle ; extra == 'test'
Requires-Dist: pyflakes ; extra == 'test'
Requires-Dist: pylint ; extra == 'test'
Requires-Dist: flake8 ; extra == 'test'
Requires-Dist: mypy ; extra == 'test'
Requires-Dist: pytest ; extra == 'test'
Requires-Dist: python-coveralls ; extra == 'test'
Requires-Dist: beautifulsoup4 ; extra == 'test'
